ansible_semaphore_api-2.9.37.data/data/requirements.txt
api/__init__.py
api/authentication_api.py
api/default_api.py
api/project_api.py
api/projects_api.py
api/schedule_api.py
api/user_api.py
models/__init__.py
models/access_key.py
models/access_key_request.py
models/access_key_request_login_password.py
models/access_key_request_ssh.py
models/api_token.py
models/environment.py
models/environment_request.py
models/event.py
models/info_type.py
models/info_type_update.py
models/inventory.py
models/inventory_request.py
models/login.py
models/login_metadata.py
models/login_metadata_oidc_providers_inner.py
models/project.py
models/project_project_id_put_request.py
models/project_project_id_role_get200_response.py
models/project_project_id_tasks_post_request.py
models/project_project_id_users_post_request.py
models/project_project_id_users_user_id_put_request.py
models/project_request.py
models/project_user.py
models/repository.py
models/repository_request.py
models/runner.py
models/schedule.py
models/schedule_request.py
models/task.py
models/task_output.py
models/template.py
models/template_request.py
models/template_survey_var.py
models/user.py
models/user_put_request.py
models/user_request.py
models/users_user_id_password_post_request.py
models/view.py
models/view_request.py
ansible_semaphore_api-2.9.37.dist-info/METADATA
ansible_semaphore_api-2.9.37.dist-info/WHEEL
ansible_semaphore_api-2.9.37.dist-info/top_level.txt
ansible_semaphore_api-2.9.37.dist-info/RECORD
