Metadata-Version: 2.1
Name: ansible-semaphore-api
Version: 2.9.37
Summary: Ansible Semaphore Python API
Home-page: https://github.com/nchekwa/ansible-semaphore-api
Author: Nchekwa
Author-email: artur@nchekwa.com
Keywords: ansible-semaphore,ansible,api
Classifier: Programming Language :: Python :: 3
Classifier: Programming Language :: Python :: 3.7
Classifier: Programming Language :: Python :: 3.8
Classifier: Programming Language :: Python :: 3.9
Classifier: Programming Language :: Python :: 3.10
Classifier: Programming Language :: Python :: 3.11
Classifier: Programming Language :: Python :: 3.12
Requires-Dist: python-dateutil >=2.5.3
Requires-Dist: setuptools >=21.0.0
Requires-Dist: urllib3 <2.1.0,>=1.25.3
Requires-Dist: pydantic >=2
Requires-Dist: typing-extensions >=4.7.1
